nerd_dictation_gui/__init__.py
nerd_dictation_gui/main.py
nerd_dictation_gui/resources/mic_idle.png
nerd_dictation_gui/resources/mic_recording.png
nerd_dictation_gui-0.1.0.dist-info/licenses/LICENSE
nerd_dictation_gui-0.1.0.dist-info/METADATA
nerd_dictation_gui-0.1.0.dist-info/WHEEL
nerd_dictation_gui-0.1.0.dist-info/entry_points.txt
nerd_dictation_gui-0.1.0.dist-info/top_level.txt
nerd_dictation_gui-0.1.0.dist-info/RECORD
