Metadata-Version: 2.4
Name: nerd-dictation-gui
Version: 0.1.0
Summary: GUI for nerd-dictation
Author: Karl Haines
Author-email: kmhnashville@gmail.com
Keywords: dictation,speech-to-text,gui
Requires-Python: >=3.6
License-File: LICENSE
Requires-Dist: PyQt6>=6.0.0
Dynamic: author
Dynamic: author-email
Dynamic: keywords
Dynamic: license-file
Dynamic: requires-dist
Dynamic: requires-python
Dynamic: summary
